Metadata-Version: 1.0
Name: gaussbidistributions
Version: 1.1
Summary: Gaussian Binomial distributions
Home-page: UNKNOWN
Author: Hina Tariq
Author-email: hina.tarique@gmail.com
License: UNKNOWN
Platform: UNKNOWN
